django_testcontainers_plus/__init__.py
django_testcontainers_plus/exceptions.py
django_testcontainers_plus/manager.py
django_testcontainers_plus/py.typed
django_testcontainers_plus/pytest_plugin.py
django_testcontainers_plus/runner.py
django_testcontainers_plus/providers/__init__.py
django_testcontainers_plus/providers/base.py
django_testcontainers_plus/providers/mysql.py
django_testcontainers_plus/providers/postgres.py
django_testcontainers_plus/providers/redis.py
django_testcontainers_plus-0.1.3.dist-info/METADATA
django_testcontainers_plus-0.1.3.dist-info/WHEEL
django_testcontainers_plus-0.1.3.dist-info/licenses/LICENSE
django_testcontainers_plus-0.1.3.dist-info/RECORD
