Metadata-Version: 2.4
Name: django-testcontainers-plus
Version: 0.1.3
Summary: A plug-and-play testcontainers integration for Django - supports databases, Redis, MinIO, and more
Project-URL: Homepage, https://github.com/woodywoodster/django-testcontainers-plus
Project-URL: Repository, https://github.com/woodywoodster/django-testcontainers-plus
Project-URL: Documentation, https://github.com/woodywoodster/django-testcontainers-plus#readme
Project-URL: Issues, https://github.com/woodywoodster/django-testcontainers-plus/issues
Author-email: Andrew Woodward <arwoodward553@gmail.com>
License: MIT
License-File: LICENSE
Keywords: containers,django,docker,mysql,postgres,redis,testcontainers,testing
Classifier: Development Status :: 3 - Alpha
Classifier: Framework :: Django
Classifier: Framework :: Django :: 4.2
Classifier: Framework :: Django :: 5.0
Classifier: Framework :: Django :: 5.1
Classifier: Framework :: Pytest
Classifier: Intended Audience :: Developers
Classifier: License :: OSI Approved :: MIT License
Classifier: Operating System :: OS Independent
Classifier: Programming Language :: Python :: 3
Classifier: Programming Language :: Python :: 3.10
Classifier: Programming Language :: Python :: 3.11
Classifier: Programming Language :: Python :: 3.12
Classifier: Programming Language :: Python :: 3.13
Classifier: Programming Language :: Python :: 3.14
Classifier: Topic :: Software Development :: Libraries :: Python Modules
Classifier: Topic :: Software Development :: Testing
Requires-Python: >=3.10
Requires-Dist: django>=4.2
Requires-Dist: pytest>=9.0.1
Requires-Dist: testcontainers>=4.0.0
Provides-Extra: all
Requires-Dist: mysql-connector-python>=8.0.0; extra == 'all'
Requires-Dist: redis>=5.0.0; extra == 'all'
Provides-Extra: dev
Requires-Dist: django-stubs>=4.2.0; extra == 'dev'
Requires-Dist: mypy>=1.8.0; extra == 'dev'
Requires-Dist: pytest-cov>=4.1.0; extra == 'dev'
Requires-Dist: pytest-django>=4.5.0; extra == 'dev'
Requires-Dist: pytest>=8.0.0; extra == 'dev'
Requires-Dist: ruff>=0.8.0; extra == 'dev'
Provides-Extra: mysql
Requires-Dist: mysql-connector-python>=8.0.0; extra == 'mysql'
Provides-Extra: redis
Requires-Dist: redis>=5.0.0; extra == 'redis'
